rsnl/__init__.py
rsnl/inference.py
rsnl/matlab_engine_manager.py
rsnl/model.py
rsnl/utils.py
rsnl/visualisations.py
rsnl-0.0.19.dist-info/LICENSE
rsnl-0.0.19.dist-info/METADATA
rsnl-0.0.19.dist-info/WHEEL
rsnl-0.0.19.dist-info/top_level.txt
rsnl-0.0.19.dist-info/RECORD
