Metadata-Version: 2.1
Name: rsnl
Version: 0.0.19
Summary: Package for RSNL algorithm for                    simulation-based inference
License: GPL
Requires-Python: >=3.7
License-File: LICENSE
Requires-Dist: jax >=0.2.0
Requires-Dist: scipy >=0.19
Requires-Dist: numpyro >=0.7.0
Requires-Dist: flowjax >=0.0.1
Requires-Dist: equinox <=0.9.0
Requires-Dist: matplotlib >=3.3.4
Requires-Dist: arviz >=0.11.2
Requires-Dist: latex >=0.7.0
Requires-Dist: diffrax >=0.0.1
Requires-Dist: psutil >=5.8.0
